fxmoney/__init__.py
fxmoney/__main__.py
fxmoney/cli.py
fxmoney/config.py
fxmoney/core.py
fxmoney/json_support.py
fxmoney/updater.py
fxmoney/rates/__init__.py
fxmoney/rates/ecb.py
fxmoney/rates/exceptions.py
fxmoney/rates/host.py
fxmoney-0.1.2.dist-info/METADATA
fxmoney-0.1.2.dist-info/WHEEL
fxmoney-0.1.2.dist-info/entry_points.txt
fxmoney-0.1.2.dist-info/licenses/LICENSE
fxmoney-0.1.2.dist-info/RECORD
