Metadata-Version: 2.4
Name: fxmoney
Version: 0.1.2
Summary: Lightweight Python library for precise money arithmetic with pluggable FX-rate backends, automatic currency conversion, and clean JSON serialization.
Project-URL: Homepage, https://github.com/feseib/fxmoney
Project-URL: Source, https://github.com/feseib/fxmoney
Project-URL: Issues, https://github.com/feseib/fxmoney/issues
Author-email: "Felix S." <feseib@users.noreply.github.com>
License: MIT
License-File: LICENSE
Keywords: currency,exchange rates,financial math,fx,money
Classifier: Development Status :: 3 - Alpha
Classifier: Intended Audience :: Developers
Classifier: License :: OSI Approved :: MIT License
Classifier: Programming Language :: Python :: 3
Classifier: Programming Language :: Python :: 3 :: Only
Classifier: Programming Language :: Python :: 3.9
Classifier: Programming Language :: Python :: 3.10
Classifier: Programming Language :: Python :: 3.11
Classifier: Topic :: Office/Business :: Financial
Classifier: Topic :: Software Development :: Libraries :: Python Modules
Requires-Python: >=3.9
Requires-Dist: pydantic<2.12,>=2.11
Requires-Dist: requests>=2.31
Provides-Extra: dev
Requires-Dist: build; extra == 'dev'
Requires-Dist: pytest; extra == 'dev'
Requires-Dist: pytest-asyncio>=0.21; extra == 'dev'
Requires-Dist: ruff; extra == 'dev'
Provides-Extra: test
Requires-Dist: pytest>=7; extra == 'test'
